{"v":"5.7.12","fr":60,"ip":0,"op":169,"w":1000,"h":1000,"nm":"web dev icon","ddd":0,"assets":[],"fonts":{"list":[{"fName":"Poppins-Bold","fFamily":"Poppins","fStyle":"Bold","ascent":78.1119004618376}]},"layers":[{"ddd":0,"ind":1,"ty":3,"nm":"Null 1","sr":1,"ks":{"o":{"a":0,"k":0,"ix":11},"r":{"a":0,"k":0,"ix":10},"p":{"a":0,"k":[500,500,0],"ix":2,"l":2},"a":{"a":0,"k":[0,0,0],"ix":1,"l":2},"s":{"a":0,"k":[100,100,100],"ix":6,"l":2}},"ao":0,"ip":0,"op":625,"st":0,"bm":0},{"ddd":0,"ind":2,"ty":4,"nm":"right >","parent":1,"sr":1,"ks":{"o":{"a":0,"k":100,"ix":11},"r":{"a":0,"k":0,"ix":10},"p":{"a":1,"k":[{"i":{"x":0.272,"y":1},"o":{"x":0.432,"y":0},"t":0,"s":[144,0,0],"to":[37.833,0,0],"ti":[-37.833,0,0]},{"i":{"x":0.667,"y":0.667},"o":{"x":0.39,"y":0.39},"t":60,"s":[371,0,0],"to":[0,0,0],"ti":[0,0,0]},{"i":{"x":0,"y":1},"o":{"x":0.171,"y":0},"t":90,"s":[371,0,0],"to":[-36.5,0,0],"ti":[36.5,0,0]},{"t":150,"s":[152,0,0]}],"ix":2,"l":2},"a":{"a":0,"k":[154.75,208.75,0],"ix":1,"l":2},"s":{"a":0,"k":[-100,100,100],"ix":6,"l":2}},"ao":0,"shapes":[{"ty":"gr","it":[{"ind":0,"ty":"sh","ix":1,"ks":{"a":1,"k":[{"i":{"x":0,"y":1},"o":{"x":0.141,"y":0},"t":0,"s":[{"i":[[0,0],[0,0],[0,0]],"o":[[0,0],[0,0],[0,0]],"v":[[52.25,-108.75],[-54.75,-1.75],[54.75,108.75]],"c":false}]},{"i":{"x":0.667,"y":1},"o":{"x":0.333,"y":0},"t":47,"s":[{"i":[[0,0],[0,0],[0,0]],"o":[[0,0],[0,0],[0,0]],"v":[[52.61,-70.75],[-54.75,-1.75],[54.61,66.75]],"c":false}]},{"i":{"x":0.667,"y":1},"o":{"x":0.333,"y":0},"t":54,"s":[{"i":[[0,0],[0,0],[0,0]],"o":[[0,0],[0,0],[0,0]],"v":[[-12.523,-142.705],[-54.75,-1.75],[-6.523,136.205]],"c":false}]},{"i":{"x":0.667,"y":1},"o":{"x":1,"y":0},"t":60,"s":[{"i":[[0,0],[0,0],[0,0]],"o":[[0,0],[0,0],[0,0]],"v":[[52.25,-108.75],[-54.75,-1.75],[54.75,108.75]],"c":false}]},{"i":{"x":0.838,"y":1},"o":{"x":1,"y":0},"t":77,"s":[{"i":[[0,0],[0,0],[0,0]],"o":[[0,0],[0,0],[0,0]],"v":[[52.25,-108.75],[-54.75,-1.75],[54.75,108.75]],"c":false}]},{"i":{"x":0,"y":1},"o":{"x":0.01,"y":0},"t":102,"s":[{"i":[[0,0],[0,0],[0,0]],"o":[[0,0],[0,0],[0,0]],"v":[[-12.523,-142.705],[-54.75,-1.75],[-6.523,136.205]],"c":false}]},{"i":{"x":0.125,"y":1},"o":{"x":0.333,"y":0},"t":113,"s":[{"i":[[0,0],[0,0],[0,0]],"o":[[0,0],[0,0],[0,0]],"v":[[52.61,-70.75],[-54.75,-1.75],[54.61,66.75]],"c":false}]},{"t":124,"s":[{"i":[[0,0],[0,0],[0,0]],"o":[[0,0],[0,0],[0,0]],"v":[[52.25,-108.75],[-54.75,-1.75],[54.75,108.75]],"c":false}]}],"ix":2},"nm":"Path 1","mn":"ADBE Vector Shape - Group","hd":false},{"ty":"st","c":{"a":0,"k":[0,1,0.635294117647,1],"ix":3},"o":{"a":0,"k":100,"ix":4},"w":{"a":0,"k":40,"ix":5},"lc":2,"lj":2,"bm":0,"nm":"Stroke 1","mn":"ADBE Vector Graphic - Stroke","hd":false},{"ty":"tr","p":{"a":0,"k":[154.75,208.75],"ix":2},"a":{"a":0,"k":[0,0],"ix":1},"s":{"a":0,"k":[100,100],"ix":3},"r":{"a":0,"k":0,"ix":6},"o":{"a":0,"k":100,"ix":7},"sk":{"a":0,"k":0,"ix":4},"sa":{"a":0,"k":0,"ix":5},"nm":"Transform"}],"nm":"Group 1","np":2,"cix":2,"bm":0,"ix":1,"mn":"ADBE Vector Group","hd":false}],"ip":0,"op":625,"st":0,"bm":0},{"ddd":0,"ind":3,"ty":4,"nm":"left <","parent":1,"sr":1,"ks":{"o":{"a":0,"k":100,"ix":11},"r":{"a":0,"k":0,"ix":10},"p":{"a":1,"k":[{"i":{"x":0.178,"y":1},"o":{"x":0.517,"y":0},"t":0,"s":[-149,0,0],"to":[-36.833,0,0],"ti":[36.833,0,0]},{"i":{"x":0.178,"y":0.178},"o":{"x":1,"y":1},"t":60,"s":[-370,0,0],"to":[0,0,0],"ti":[0,0,0]},{"i":{"x":0.178,"y":0.178},"o":{"x":1,"y":1},"t":77,"s":[-370,0,0],"to":[0,0,0],"ti":[0,0,0]},{"i":{"x":0,"y":1},"o":{"x":0.256,"y":0},"t":90,"s":[-370,0,0],"to":[37.667,0,0],"ti":[-37.667,0,0]},{"t":150,"s":[-144,0,0]}],"ix":2,"l":2},"a":{"a":0,"k":[154.75,208.75,0],"ix":1,"l":2},"s":{"a":0,"k":[100,100,100],"ix":6,"l":2}},"ao":0,"shapes":[{"ty":"gr","it":[{"ind":0,"ty":"sh","ix":1,"ks":{"a":1,"k":[{"i":{"x":0,"y":1},"o":{"x":0.141,"y":0},"t":0,"s":[{"i":[[0,0],[0,0],[0,0]],"o":[[0,0],[0,0],[0,0]],"v":[[52.25,-108.75],[-54.75,-1.75],[54.75,108.75]],"c":false}]},{"i":{"x":0.667,"y":1},"o":{"x":0.333,"y":0},"t":47,"s":[{"i":[[0,0],[0,0],[0,0]],"o":[[0,0],[0,0],[0,0]],"v":[[52.61,-70.75],[-54.75,-1.75],[54.61,66.75]],"c":false}]},{"i":{"x":0.667,"y":1},"o":{"x":0.333,"y":0},"t":54,"s":[{"i":[[0,0],[0,0],[0,0]],"o":[[0,0],[0,0],[0,0]],"v":[[-12.523,-142.705],[-54.75,-1.75],[-6.523,136.205]],"c":false}]},{"i":{"x":0.838,"y":1},"o":{"x":1,"y":0},"t":60,"s":[{"i":[[0,0],[0,0],[0,0]],"o":[[0,0],[0,0],[0,0]],"v":[[52.25,-108.75],[-54.75,-1.75],[54.75,108.75]],"c":false}]},{"i":{"x":0,"y":1},"o":{"x":0.01,"y":0},"t":102,"s":[{"i":[[0,0],[0,0],[0,0]],"o":[[0,0],[0,0],[0,0]],"v":[[-12.523,-142.705],[-54.75,-1.75],[-6.523,136.205]],"c":false}]},{"i":{"x":0.125,"y":1},"o":{"x":0.333,"y":0},"t":113,"s":[{"i":[[0,0],[0,0],[0,0]],"o":[[0,0],[0,0],[0,0]],"v":[[52.61,-70.75],[-54.75,-1.75],[54.61,66.75]],"c":false}]},{"t":124,"s":[{"i":[[0,0],[0,0],[0,0]],"o":[[0,0],[0,0],[0,0]],"v":[[52.25,-108.75],[-54.75,-1.75],[54.75,108.75]],"c":false}]}],"ix":2},"nm":"Path 1","mn":"ADBE Vector Shape - Group","hd":false},{"ty":"st","c":{"a":0,"k":[0,1,0.635294117647,1],"ix":3},"o":{"a":0,"k":100,"ix":4},"w":{"a":0,"k":40,"ix":5},"lc":2,"lj":2,"bm":0,"nm":"Stroke 1","mn":"ADBE Vector Graphic - Stroke","hd":false},{"ty":"tr","p":{"a":0,"k":[154.75,208.75],"ix":2},"a":{"a":0,"k":[0,0],"ix":1},"s":{"a":0,"k":[100,100],"ix":3},"r":{"a":0,"k":0,"ix":6},"o":{"a":0,"k":100,"ix":7},"sk":{"a":0,"k":0,"ix":4},"sa":{"a":0,"k":0,"ix":5},"nm":"Transform"}],"nm":"Group 1","np":2,"cix":2,"bm":0,"ix":1,"mn":"ADBE Vector Group","hd":false}],"ip":0,"op":625,"st":0,"bm":0},{"ddd":0,"ind":4,"ty":4,"nm":"slash","parent":2,"sr":1,"ks":{"o":{"a":0,"k":100,"ix":11},"r":{"a":1,"k":[{"i":{"x":[0.667],"y":[1]},"o":{"x":[0.333],"y":[0]},"t":0,"s":[0]},{"i":{"x":[0.667],"y":[2]},"o":{"x":[0.333],"y":[0]},"t":49,"s":[8]},{"i":{"x":[0.667],"y":[1]},"o":{"x":[0.333],"y":[0.6]},"t":53,"s":[10]},{"i":{"x":[0.667],"y":[1]},"o":{"x":[1],"y":[0]},"t":65,"s":[0]},{"i":{"x":[0.833],"y":[1]},"o":{"x":[1],"y":[0]},"t":86,"s":[0]},{"i":{"x":[0.667],"y":[1]},"o":{"x":[0.167],"y":[0]},"t":101,"s":[15]},{"t":111,"s":[0]}],"ix":10},"p":{"a":0,"k":[278.75,208.75,0],"ix":2,"l":2},"a":{"a":0,"k":[52.893,180.157,0],"ix":1,"l":2},"s":{"a":0,"k":[-100,100,100],"ix":6,"l":2}},"ao":0,"shapes":[{"ty":"gr","it":[{"ind":0,"ty":"sh","ix":1,"ks":{"a":0,"k":{"i":[[0,0],[0,0]],"o":[[0,0],[0,0]],"v":[[32.893,-160.157],[-32.893,160.157]],"c":false},"ix":2},"nm":"Path 1","mn":"ADBE Vector Shape - Group","hd":false},{"ty":"st","c":{"a":0,"k":[0,1,0.635294117647,1],"ix":3},"o":{"a":0,"k":100,"ix":4},"w":{"a":0,"k":40,"ix":5},"lc":2,"lj":2,"bm":0,"nm":"Stroke 1","mn":"ADBE Vector Graphic - Stroke","hd":false},{"ty":"st","c":{"a":0,"k":[0,1,0.635294117647,1],"ix":3},"o":{"a":0,"k":100,"ix":4},"w":{"a":0,"k":40,"ix":5},"lc":2,"lj":2,"bm":0,"nm":"Stroke 2","mn":"ADBE Vector Graphic - Stroke","hd":false},{"ty":"tr","p":{"a":0,"k":[52.892,180.157],"ix":2},"a":{"a":0,"k":[0,0],"ix":1},"s":{"a":0,"k":[100,100],"ix":3},"r":{"a":0,"k":0,"ix":6},"o":{"a":0,"k":100,"ix":7},"sk":{"a":0,"k":0,"ix":4},"sa":{"a":0,"k":0,"ix":5},"nm":"Transform"}],"nm":"Group 1","np":3,"cix":2,"bm":0,"ix":1,"mn":"ADBE Vector Group","hd":false}],"ip":0,"op":625,"st":0,"bm":0},{"ddd":0,"ind":5,"ty":5,"nm":"br","parent":3,"sr":1,"ks":{"o":{"a":1,"k":[{"i":{"x":[0.833],"y":[0.833]},"o":{"x":[0.167],"y":[0.167]},"t":46,"s":[0]},{"i":{"x":[0.833],"y":[0.833]},"o":{"x":[0.167],"y":[0.167]},"t":47,"s":[100]},{"i":{"x":[0.833],"y":[0.833]},"o":{"x":[0.167],"y":[0.167]},"t":101,"s":[100]},{"t":102,"s":[0]}],"ix":11},"r":{"a":0,"k":0,"ix":10},"p":{"a":0,"k":[257.75,290.75,0],"ix":2,"l":2},"a":{"a":0,"k":[0,0,0],"ix":1,"l":2},"s":{"a":0,"k":[100,100,100],"ix":6,"l":2}},"ao":0,"t":{"d":{"k":[{"s":{"s":400,"f":"Poppins-Bold","t":"br","ca":0,"j":0,"tr":32,"lh":480,"ls":-32,"fc":[1,1,1],"sc":[0,0,0],"sw":0.00999999977648,"of":false},"t":0}]},"p":{},"m":{"g":1,"a":{"a":0,"k":[0,0],"ix":2}},"a":[{"nm":"Animator 1","s":{"t":0,"xe":{"a":0,"k":100,"ix":7},"ne":{"a":0,"k":-100,"ix":8},"a":{"a":0,"k":100,"ix":4},"b":1,"rn":0,"sh":6,"r":1},"a":{"p":{"a":1,"k":[{"i":{"x":0.667,"y":0.827},"o":{"x":1,"y":0},"t":47,"s":[0,65,0],"to":[0,-7.571,0],"ti":[0,17.131,0]},{"i":{"x":0.667,"y":1},"o":{"x":0.333,"y":0.202},"t":55,"s":[0,-46.148,0],"to":[0,-7.381,0],"ti":[0,3.262,0]},{"i":{"x":0.667,"y":1},"o":{"x":0.167,"y":0},"t":59,"s":[0,0,0],"to":[0,-10.833,0],"ti":[0,-3.262,0]},{"i":{"x":0.054,"y":0.496},"o":{"x":0.333,"y":0},"t":82,"s":[0,0,0],"to":[0,3.262,0],"ti":[0,-7.381,0]},{"i":{"x":0.892,"y":1},"o":{"x":1,"y":0.437},"t":88.041,"s":[0,-46.148,0],"to":[0,17.131,0],"ti":[0,-7.571,0]},{"t":100.123046875,"s":[0,65,0]}],"ix":2},"o":{"a":1,"k":[{"i":{"x":[0.667],"y":[1]},"o":{"x":[0.333],"y":[0]},"t":47,"s":[0]},{"i":{"x":[0.667],"y":[1]},"o":{"x":[0.167],"y":[0]},"t":59,"s":[100]},{"i":{"x":[0.667],"y":[1]},"o":{"x":[0.333],"y":[0]},"t":82,"s":[100]},{"t":100.123046875,"s":[0]}],"ix":9}}}]},"ip":0,"op":625,"st":0,"bm":0}],"markers":[],"chars":[{"ch":"b","size":400,"style":"Bold","w":67.9,"data":{"shapes":[{"ty":"gr","it":[{"ind":0,"ty":"sh","ix":1,"ks":{"a":0,"k":{"i":[[1.6,-2.6],[0,0],[0,0],[0,0],[0,0],[0,0],[-2.934,-1.566],[-3.934,0],[-3.734,2.367],[-2.167,4.367],[0,5.734],[2.166,4.334],[3.733,2.334],[4.6,0],[3,-1.6]],"o":[[0,0],[0,0],[0,0],[0,0],[0,0],[1.666,2.6],[2.933,1.566],[4.6,0],[3.733,-2.366],[2.166,-4.366],[0,-5.733],[-2.167,-4.333],[-3.734,-2.333],[-3.867,0],[-3,1.6]],"v":[[23.3,-47.9],[23.3,-74],[6.2,-74],[6.2,0],[23.3,0],[23.3,-7.8],[30.2,-1.55],[40.5,0.8],[53,-2.75],[61.85,-12.85],[65.1,-28],[61.85,-43.1],[53,-53.1],[40.5,-56.6],[30.2,-54.2]],"c":true},"ix":2},"nm":"b","mn":"ADBE Vector Shape - Group","hd":false},{"ind":1,"ty":"sh","ix":2,"ks":{"a":0,"k":{"i":[[0,-4.266],[2.4,-2.5],[3.4,0],[2.366,2.467],[0,4.267],[-2.367,2.467],[-3.4,0],[-2.367,-2.433]],"o":[[0,4.267],[-2.4,2.5],[-3.4,0],[-2.367,-2.466],[0,-4.266],[2.366,-2.466],[3.466,0],[2.366,2.434]],"v":[[47.7,-28],[44.1,-17.85],[35.4,-14.1],[26.75,-17.8],[23.2,-27.9],[26.75,-38],[35.4,-41.7],[44.15,-38.05]],"c":true},"ix":2},"nm":"b","mn":"ADBE Vector Shape - Group","hd":false}],"nm":"b","np":5,"cix":2,"bm":0,"ix":1,"mn":"ADBE Vector Group","hd":false}]},"fFamily":"Poppins"},{"ch":"r","size":400,"style":"Bold","w":42.8,"data":{"shapes":[{"ty":"gr","it":[{"ind":0,"ty":"sh","ix":1,"ks":{"a":0,"k":{"i":[[2,-3.066],[0,0],[0,0],[0,0],[0,0],[0,0],[-2.134,1.834],[-4.267,0],[0,0],[0,0],[3,-1.766]],"o":[[0,0],[0,0],[0,0],[0,0],[0,0],[0,-4.6],[2.133,-1.833],[0,0],[0,0],[-3.667,0],[-3,1.767]],"v":[[23.3,-46.5],[23.3,-55.8],[6.2,-55.8],[6.2,0],[23.3,0],[23.3,-25.9],[26.5,-35.55],[36.1,-38.3],[40.8,-38.3],[40.8,-56.4],[30.8,-53.75]],"c":true},"ix":2},"nm":"r","mn":"ADBE Vector Shape - Group","hd":false}],"nm":"r","np":3,"cix":2,"bm":0,"ix":1,"mn":"ADBE Vector Group","hd":false}]},"fFamily":"Poppins"}]}